zscryptography/__init__.py
zscryptography/zscryptography.py
zscryptography-2.0.0.dist-info/METADATA
zscryptography-2.0.0.dist-info/WHEEL
zscryptography-2.0.0.dist-info/top_level.txt
zscryptography-2.0.0.dist-info/RECORD
