Metadata-Version: 2.1
Name: zscryptography
Version: 2.0.0
Summary: A simple cryptography library using AES
Home-page: https://github.com/zsu/zscryptography
Author: ZSU
Author-email: 
Classifier: Programming Language :: Python :: 3
Classifier: License :: OSI Approved :: MIT License
Classifier: Operating System :: OS Independent
Requires-Python: >=3.6
Requires-Dist: cryptography
